{
  "$schema": "https://design-tokens.github.io/community-group/format/",
  "name": "magi-ui-tokens",
  "version": "1.0.0",
  "meta": {
    "source": [
      "frontend/tailwind.config.ts",
      "frontend/app/globals.css",
      "frontend/app/layout.tsx"
    ],
    "description": "Design tokens extracted from MAGI frontend for Figma Variables import"
  },
  "color": {
    "terminal": {
      "bg": { "value": "#04070c" },
      "panel": { "value": "#09111a" },
      "border": { "value": "#1a3248" },
      "text": { "value": "#d5e7f7" },
      "dim": { "value": "#89a4bc" },
      "ok": { "value": "#72f0a0" },
      "err": { "value": "#ff6f7f" },
      "accent": { "value": "#ff8a5c" }
    },
    "surface": {
      "deep": { "value": "#02060b" },
      "ink": { "value": "#050a10" },
      "wire": { "value": "#0d1d2a" }
    },
    "overlay": {
      "blueSoft": { "value": "rgba(83, 170, 228, 0.14)" },
      "orangeSoft": { "value": "rgba(255, 102, 60, 0.13)" },
      "blueMid": { "value": "rgba(25, 65, 110, 0.20)" }
    }
  },
  "typography": {
    "fontFamily": {
      "base": {
        "value": "Space Grotesk, Segoe UI, Hiragino Kaku Gothic ProN, Yu Gothic, sans-serif"
      }
    },
    "fontSize": {
      "xs": { "value": "12px" },
      "sm": { "value": "14px" },
      "base": { "value": "16px" },
      "lg": { "value": "18px" },
      "xl": { "value": "20px" },
      "2xl": { "value": "24px" }
    },
    "fontWeight": {
      "regular": { "value": "400" },
      "semibold": { "value": "600" },
      "bold": { "value": "700" },
      "black": { "value": "900" }
    },
    "lineHeight": {
      "tight": { "value": "1.25" },
      "normal": { "value": "1.5" },
      "relaxed": { "value": "1.7" }
    },
    "letterSpacing": {
      "wide": { "value": "0.07em" },
      "wider": { "value": "0.2em" }
    }
  },
  "spacing": {
    "0": { "value": "0px" },
    "1": { "value": "4px" },
    "2": { "value": "8px" },
    "3": { "value": "12px" },
    "4": { "value": "16px" },
    "6": { "value": "24px" },
    "8": { "value": "32px" }
  },
  "radius": {
    "sm": { "value": "4px" },
    "md": { "value": "6px" },
    "lg": { "value": "8px" },
    "xl": { "value": "12px" },
    "2xl": { "value": "16px" },
    "full": { "value": "999px" }
  },
  "border": {
    "panel": {
      "width": { "value": "1px" },
      "color": { "value": "{color.terminal.border}" }
    },
    "node": {
      "width": { "value": "2px" },
      "color": { "value": "#ff7449" }
    }
  },
  "shadow": {
    "panel": {
      "value": "inset 0 1px 0 rgba(110,206,255,0.16), inset 0 -1px 0 rgba(255,124,82,0.18), 0 14px 34px rgba(0,0,0,0.45)"
    },
    "nodeDefault": {
      "value": "0 0 0 1px rgba(52,98,147,0.4) inset, 0 16px 30px rgba(0,0,0,0.38)"
    },
    "nodeOn": {
      "value": "0 0 0 1px rgba(117,77,49,0.52) inset, 0 0 20px rgba(255,190,116,0.42), 0 14px 28px rgba(0,0,0,0.34)"
    }
  },
  "motion": {
    "duration": {
      "fast": { "value": "150ms" },
      "normal": { "value": "250ms" },
      "blink": { "value": "850ms" },
      "progress": { "value": "1100ms" }
    },
    "easing": {
      "standard": { "value": "ease" },
      "linear": { "value": "linear" }
    }
  }
}
